odoo/addons/l10n_de_mis_reports/README.rst
odoo/addons/l10n_de_mis_reports/__init__.py
odoo/addons/l10n_de_mis_reports/__manifest__.py
odoo/addons/l10n_de_mis_reports/data/mis_report_bs_skr03.xml
odoo/addons/l10n_de_mis_reports/data/mis_report_bs_skr04.xml
odoo/addons/l10n_de_mis_reports/data/mis_report_pl_skr03.xml
odoo/addons/l10n_de_mis_reports/data/mis_report_pl_skr04.xml
odoo/addons/l10n_de_mis_reports/data/mis_report_styles.xml
odoo/addons/l10n_de_mis_reports/i18n/de.po
odoo/addons/l10n_de_mis_reports/i18n/l10n_de_mis_reports.pot
odoo/addons/l10n_de_mis_reports/i18n/l10n_de_skr04_mis_reports.pot
odoo/addons/l10n_de_mis_reports/static/description/icon.png
odoo_addon_l10n_de_mis_reports-17.0.1.1.2.dist-info/METADATA
odoo_addon_l10n_de_mis_reports-17.0.1.1.2.dist-info/WHEEL
odoo_addon_l10n_de_mis_reports-17.0.1.1.2.dist-info/top_level.txt
odoo_addon_l10n_de_mis_reports-17.0.1.1.2.dist-info/RECORD
